btfx_trader/__init__.py
btfx_trader/private.py
btfx_trader/public.py
btfx_trader-0.1.6.dist-info/METADATA
btfx_trader-0.1.6.dist-info/RECORD
btfx_trader-0.1.6.dist-info/WHEEL
btfx_trader-0.1.6.dist-info/top_level.txt
