Metadata-Version: 2.1
Name: btfx-trader
Version: 0.1.6
Summary: Simple to use wrappers for the Bitfinex web socket api
Home-page: https://github.com/sentrip/btfx_trader
Author: Djordje Pepic
Author-email: djordje.m.pepic@gmail.com
License: GNU General Public License v3
Keywords: btfx_trader
Platform: UNKNOWN
Classifier: Development Status :: 2 - Pre-Alpha
Classifier: Intended Audience :: Developers
Classifier: License :: OSI Approved :: GNU General Public License v3 (GPLv3)
Classifier: Natural Language :: English
Classifier: Programming Language :: Python :: 3.5
Classifier: Programming Language :: Python :: 3.6
Requires-Dist: btfxwss (==1.1.16)
Requires-Dist: requests (==2.19.1)
